pagerduty_advance_mcp/__init__.py
pagerduty_advance_mcp/__main__.py
pagerduty_advance_mcp/client.py
pagerduty_advance_mcp/server.py
pagerduty_advance_mcp/models/__init__.py
pagerduty_advance_mcp/models/advance_chat.py
pagerduty_advance_mcp/tools/__init__.py
pagerduty_advance_mcp/tools/advance_chat_request.py
pagerduty_advance_mcp-0.0.9.dist-info/licenses/LICENSE
pagerduty_advance_mcp-0.0.9.dist-info/METADATA
pagerduty_advance_mcp-0.0.9.dist-info/WHEEL
pagerduty_advance_mcp-0.0.9.dist-info/entry_points.txt
pagerduty_advance_mcp-0.0.9.dist-info/top_level.txt
pagerduty_advance_mcp-0.0.9.dist-info/RECORD
