Metadata-Version: 2.4
Name: pagerduty_advance_mcp
Version: 0.0.9
Summary: PagerDuty's official local MCP (Model Context Protocol) server which provides tools to interact with PagerDuty AI Agent directly from your MCP-enabled client.
Requires-Python: <3.13,>=3.12
License-File: LICENSE
Requires-Dist: mcp[cli]>=1.8.0
Requires-Dist: pagerduty>=5.3.0
Requires-Dist: typer>=0.16.0
Dynamic: license-file
